uniq/__init__.py
uniq/Copyright
uniq/LICENSE
uniq/MANIFEST.in
uniq/README.md
uniq/README.rst
uniq/requirements.txt
uniq/uniq.png
uniq/apis/__init__.py
uniq/apis/client_manager.py
uniq/apis/exceptions.py
uniq/apis/nb/__init__.py
uniq/apis/nb/client_manager.py
uniq/apis/nb/clients/__init__.py
uniq/apis/nb/clients/api_client.py
uniq/apis/nb/clients/file_service_client/__init__.py
uniq/apis/nb/clients/file_service_client/FileApi.py
uniq/apis/nb/clients/file_service_client/fileservice.json
uniq/apis/nb/clients/file_service_client/models/__init__.py
uniq/apis/nb/clients/file_service_client/models/FileObject.py
uniq/apis/nb/clients/file_service_client/models/FileObjectListResult.py
uniq/apis/nb/clients/file_service_client/models/FileObjectResult.py
uniq/apis/nb/clients/file_service_client/models/NameSpaceListResult.py
uniq/apis/nb/clients/file_service_client/models/SuccessResult.py
uniq/apis/nb/clients/file_service_client/models/Void.py
uniq/apis/nb/clients/group_client/__init__.py
uniq/apis/nb/clients/group_client/group.json
uniq/apis/nb/clients/group_client/GroupApi.py
uniq/apis/nb/clients/group_client/models/__init__.py
uniq/apis/nb/clients/group_client/models/CountResult.py
uniq/apis/nb/clients/group_client/models/GroupMembersResult.py
uniq/apis/nb/clients/group_client/models/GroupTypesResult.py
uniq/apis/nb/clients/group_client/models/Resource.py
uniq/apis/nb/clients/group_client/models/ResourceGroupDTO.py
uniq/apis/nb/clients/group_client/models/ResourceGroupListResult.py
uniq/apis/nb/clients/group_client/models/ResourceGroupResult.py
uniq/apis/nb/clients/group_client/models/TaskIdResponse.py
uniq/apis/nb/clients/identity_manager_client/__init__.py
uniq/apis/nb/clients/identity_manager_client/cisco-ise.json
uniq/apis/nb/clients/identity_manager_client/neighborhood.json
uniq/apis/nb/clients/identity_manager_client/scalable-group.json
uniq/apis/nb/clients/identity_manager_client/V2CiscoiseApi.py
uniq/uniq.egg-info/dependency_links.txt
uniq/uniq.egg-info/PKG-INFO
uniq/uniq.egg-info/requires.txt
uniq/uniq.egg-info/SOURCES.txt
uniq/uniq.egg-info/top_level.txt
uniq-1.4.0.36.dist-info/DESCRIPTION.rst
uniq-1.4.0.36.dist-info/METADATA
uniq-1.4.0.36.dist-info/metadata.json
uniq-1.4.0.36.dist-info/RECORD
uniq-1.4.0.36.dist-info/top_level.txt
uniq-1.4.0.36.dist-info/WHEEL
