Metadata-Version: 2.0
Name: uniq
Version: 1.4.0.36
Summary: A Python API client library for Cisco's Application Policy Infrastructure Controller Enterprise Module (APIC-EM) Northbound APIs.
Home-page: UNKNOWN
Author: Amey Patil, Li Feng
Author-email: ameyspatil@gmail.com, fengli616@gmail.com
License: Apache License 2.0
Platform: unix
Platform: linux
Platform: osx
Classifier: Development Status :: 5 - Production/Stable
Classifier: License :: OSI Approved :: Apache Software License
Classifier: Programming Language :: Python :: 3 :: Only
Classifier: Programming Language :: Python :: 3.4
Classifier: Programming Language :: Python :: 3.5
Classifier: Topic :: Utilities
Requires-Dist: requests (>=2.6.0)
